pulp-stubs/__init__.pyi
pulp-stubs/constants.pyi
pulp-stubs/mps_lp.pyi
pulp-stubs/pulp.pyi
pulp-stubs/py.typed
pulp-stubs/sparse.pyi
pulp-stubs/utilities.pyi
pulp-stubs/apis/__init__.pyi
pulp-stubs/apis/choco_api.pyi
pulp-stubs/apis/coin_api.pyi
pulp-stubs/apis/copt_api.pyi
pulp-stubs/apis/core.pyi
pulp-stubs/apis/cplex_api.pyi
pulp-stubs/apis/cuopt_api.pyi
pulp-stubs/apis/glpk_api.pyi
pulp-stubs/apis/gurobi_api.pyi
pulp-stubs/apis/highs_api.pyi
pulp-stubs/apis/mipcl_api.pyi
pulp-stubs/apis/mosek_api.pyi
pulp-stubs/apis/sas_api.pyi
pulp-stubs/apis/scip_api.pyi
pulp-stubs/apis/xpress_api.pyi
pulp-stubs/solverdir/__init__.pyi
pulp_stubs-0.1.1.dist-info/METADATA
pulp_stubs-0.1.1.dist-info/WHEEL
pulp_stubs-0.1.1.dist-info/RECORD
