Metadata-Version: 2.4
Name: pulp-stubs
Version: 0.1.1
Summary: Type stubs for PuLP
Author-email: thw33ts <thweets.business@gmail.com>
Requires-Python: >=3.10
Requires-Dist: pulp==3.3.0
